cursor_mdc_generator/__init__.py
cursor_mdc_generator/cli.py
cursor_mdc_generator/code_summarization.py
cursor_mdc_generator/repo_analyzer.py
cursor_mdc_generator/repository_structure.py
cursor_mdc_generator/symbolic_graph.py
cursor_mdc_generator/visualize_dependency_graph.py
cursor_mdc_generator/llm_utils/llm_client.py
cursor_mdc_generator/llm_utils/model_lists.py
cursor_mdc_generator/llm_utils/models.py
cursor_mdc_generator/llm_utils/prompts.py
cursor_mdc_generator/llm_utils/tokenize_utils.py
mdcgen-0.1.8.dist-info/LICENSE
mdcgen-0.1.8.dist-info/METADATA
mdcgen-0.1.8.dist-info/WHEEL
mdcgen-0.1.8.dist-info/entry_points.txt
mdcgen-0.1.8.dist-info/top_level.txt
mdcgen-0.1.8.dist-info/RECORD
