Metadata-Version: 2.2
Name: mdcgen
Version: 0.1.8
Summary: A tool to generate Cursor IDE MDC files from repository analysis
Author: Cursor MDC Generator
License: MIT
Requires-Python: >=3.7
License-File: LICENSE
Requires-Dist: matplotlib
Requires-Dist: networkx
Requires-Dist: gitpython
Requires-Dist: pydantic
Requires-Dist: astroid
Requires-Dist: click
Requires-Dist: litellm
Provides-Extra: visualization
Requires-Dist: pygraphviz; extra == "visualization"
